ipynotebook/__init__.py
ipynotebook/__main__.py
ipynotebook/app.py
ipynotebook/static/index.html
ipynotebook/static/vendor/particles.min.js
ipynotebook-0.1.0.dist-info/licenses/LICENSE
ipynotebook-0.1.0.dist-info/METADATA
ipynotebook-0.1.0.dist-info/WHEEL
ipynotebook-0.1.0.dist-info/entry_points.txt
ipynotebook-0.1.0.dist-info/top_level.txt
ipynotebook-0.1.0.dist-info/RECORD
