Metadata-Version: 2.4
Name: ipynotebook
Version: 0.1.0
Summary: Desktop landing page for ipynotebook – PyWebview + React with particles.js
Author-email: Your Name <you@example.com>
License: MIT
Requires-Python: >=3.8
License-File: LICENSE
Requires-Dist: pywebview
Dynamic: license-file
